karrio/mappers/easypost/__init__.py
karrio/mappers/easypost/mapper.py
karrio/mappers/easypost/proxy.py
karrio/mappers/easypost/settings.py
karrio/plugins/easypost/__init__.py
karrio/providers/easypost/__init__.py
karrio/providers/easypost/error.py
karrio/providers/easypost/rate.py
karrio/providers/easypost/tracking.py
karrio/providers/easypost/units.py
karrio/providers/easypost/utils.py
karrio/providers/easypost/shipment/__init__.py
karrio/providers/easypost/shipment/cancel.py
karrio/providers/easypost/shipment/create.py
karrio/schemas/easypost/__init__.py
karrio/schemas/easypost/error_response.py
karrio/schemas/easypost/shipment_purchase.py
karrio/schemas/easypost/shipment_request.py
karrio/schemas/easypost/shipments_response.py
karrio/schemas/easypost/trackers_response.py
karrio_easypost-2026.1.4.dist-info/licenses/LICENSE
karrio_easypost-2026.1.4.dist-info/METADATA
karrio_easypost-2026.1.4.dist-info/WHEEL
karrio_easypost-2026.1.4.dist-info/entry_points.txt
karrio_easypost-2026.1.4.dist-info/top_level.txt
karrio_easypost-2026.1.4.dist-info/RECORD
